{"deckName":"text","mainDeck":[{"level":4,"cardType":"NORMAL","monsterTypes":["DRAGON"],"attribute":"LIGHT","attack":2000,"defense":100,"name":"Alexandrite Dragon","description":"Many of the czars\u0027 lost jewels can be found in the scales of this priceless dragon. Its creator remains a mystery, along with how they acquired the imperial treasures. But whosoever finds this dragon has hit the jackpot... whether they know it or not.","type":"monster","price":2600},{"property":"EQUIP","limitationStatus":"Unlimited","name":"Black Pendant","description":"The equipped monster gains 500 ATK. When this card is sent from the field to the Graveyard: Inflict 500 damage to your opponent.","type":"spell","price":4300},{"level":2,"cardType":"NORMAL","monsterTypes":["CYBERSE"],"attribute":"EARTH","attack":200,"defense":2000,"name":"Bitron","description":"A new species found in electronic space. There\u0027s not much information on it.","type":"monster","price":1000}],"sideDeck":[{"level":4,"cardType":"NORMAL","monsterTypes":["BEAST","WARRIOR"],"attack":1700,"defense":1000,"name":"Battle OX","description":"A monster with tremendous power, it destroys enemies with a swing of its axe.","type":"monster","price":2900}]}